[{"id": 1, "isthing": true, "category_id": 1, "xy": [7823, 2196]}, {"id": 2, "isthing": true, "category_id": 1, "xy": [3700, 2092]}, {"id": 3, "isthing": true, "category_id": 1, "xy": [6284, 2249]}, {"id": 4, "isthing": true, "category_id": 1, "xy": [4468, 2101]}, {"id": 5, "isthing": true, "category_id": 1, "xy": [2005, 2261]}, {"id": 6, "isthing": true, "category_id": 1, "xy": [7220, 2230]}, {"id": 7, "isthing": true, "category_id": 1, "xy": [2991, 2155]}, {"id": 8, "isthing": true, "category_id": 1, "xy": [435, 2213]}, {"id": 9, "isthing": true, "category_id": 1, "xy": [5300, 2161]}]